{
  "sectionCode": "10/41",
  "mappings": [
    {
      "episodeTitle": "History of History",
      "pid": "b00gryrx",
      "relevantPathsAI": [
        "A",
        "A.1",
        "A.1.a.ii",
        "A.1.c.iii",
        "A.1.c.iv"
      ],
      "rationaleAI": "Historiography from Herodotus and Thucydides through Ranke, the Annales school, and postmodern challenges directly traces the development of historical writing (A.1) across classical (A.1.a.ii), Enlightenment (A.1.c.iii), and 19th-20th century periods (A.1.c.iv)."
    },
    {
      "episodeTitle": "Thucydides",
      "pid": "b050bcf1",
      "relevantPathsAI": [
        "A.1.a.ii",
        "A.3"
      ],
      "rationaleAI": "Thucydides' methodology emphasising empirical observation and rejection of mythological explanation is foundational for classical historiography (A.1.a.ii), and his concept of human nature as constant relates to factors in historical writing (A.3)."
    },
    {
      "episodeTitle": "Edward Gibbon",
      "pid": "m000x0v2",
      "relevantPathsAI": [
        "A.1.c.iii",
        "A.3"
      ],
      "rationaleAI": "Gibbon's History of the Decline and Fall exemplifies Enlightenment historiography (A.1.c.iii) and illustrates factors in writing history including the author's rationalist vantage point (A.3)."
    },
    {
      "episodeTitle": "Ibn Khaldun",
      "pid": "b00qckbw",
      "relevantPathsAI": [
        "A.1.d.i"
      ],
      "rationaleAI": "Ibn Khaldun's Muqaddimah pioneered sociological analysis of history, making him the preeminent figure in Islamic historiography (A.1.d.i)."
    },
    {
      "episodeTitle": "Sources of Early Chinese History",
      "pid": "b03qf7qx",
      "relevantPathsAI": [
        "A.1.d.ii",
        "B.1"
      ],
      "rationaleAI": "Sources of early Chinese history including oracle bones, Sima Qian's Records, and bamboo texts address East Asian historiography (A.1.d.ii) and sources for historical writing (B.1)."
    },
    {
      "episodeTitle": "Hegel's Philosophy of History",
      "pid": "m0017k8w",
      "relevantPathsAI": [
        "C",
        "C.1",
        "C.2"
      ],
      "rationaleAI": "Hegel's philosophy of history with its dialectical method and concept of progressive consciousness of freedom is a major speculative philosophy of history (C.2) and a foundational conception of the philosophy of history (C.1)."
    },
    {
      "episodeTitle": "Progress",
      "pid": "p0054646",
      "relevantPathsAI": [
        "C.2"
      ],
      "rationaleAI": "The idea of progress from Enlightenment optimism through postmodern skepticism represents a central speculative philosophy of history concerning the pattern of historical events (C.2)."
    },
    {
      "episodeTitle": "Episode 1",
      "pid": "b018wfsc",
      "relevantPathsAI": [
        "B.1",
        "B.2.f"
      ],
      "rationaleAI": "The origins of writing from cuneiform to alphabetic script cover the development of written materials as sources for historical writing (B.1) and connect to epigraphy (B.2.f)."
    },
    {
      "episodeTitle": "The Phoenicians",
      "pid": "b03szw8l",
      "relevantPathsAI": [
        "A.1.a.i",
        "B.2.l"
      ],
      "rationaleAI": "The Phoenicians' revolutionary alphabetic writing system connects to Near Eastern historiography (A.1.a.i) and linguistics as an auxiliary discipline (B.2.l)."
    },
    {
      "episodeTitle": "The Venerable Bede",
      "pid": "p004y26h",
      "relevantPathsAI": [
        "A.1.b.i",
        "B.2.d"
      ],
      "rationaleAI": "Bede's Ecclesiastical History established the AD dating system, connecting to Western Christian historiography (A.1.b.i) and chronology as an auxiliary discipline (B.2.d)."
    },
    {
      "episodeTitle": "Cicero",
      "pid": "b09nrsfg",
      "relevantPathsAI": [
        "A.1.a.ii"
      ],
      "rationaleAI": "Cicero's philosophical works transmitting Greek thought to Rome and his influence on Renaissance humanism connect to classical historiography (A.1.a.ii)."
    },
    {
      "episodeTitle": "Strabo's Geographica",
      "pid": "b03zr11t",
      "relevantPathsAI": [
        "A.1.a.ii",
        "B.2.i"
      ],
      "rationaleAI": "Strabo's Geographica as a comprehensive description of the known world connects to classical historiography (A.1.a.ii) and geography as an auxiliary discipline (B.2.i)."
    },
    {
      "episodeTitle": "al-Biruni",
      "pid": "b00smnlk",
      "relevantPathsAI": [
        "A.1.d.i"
      ],
      "rationaleAI": "Al-Biruni's comparative study of Indian civilization in his Kitab al-Hind represents a pioneering example of Islamic historiography (A.1.d.i)."
    }
  ],
  "_curatedBy": "ai",
  "_generatedAt": "2026-03-23"
}
