{
  "sectionCode": "629",
  "mappings": [
    {
      "episodeTitle": "Bauhaus",
      "pid": "m001dxtg",
      "relevantPathsAI": [
        "A",
        "C.2",
        "C.3",
        "C.4.b"
      ],
      "rationaleAI": "The Bauhaus integrated fine art with crafts and industrial design, profoundly influencing typography, furniture design, and industrial design as an art -- core topics of functional design."
    },
    {
      "episodeTitle": "William Morris",
      "pid": "b0b9w0vq",
      "relevantPathsAI": [
        "A",
        "B.2",
        "B.6",
        "B.8",
        "C.3",
        "C.4.b"
      ],
      "rationaleAI": "William Morris's Arts and Crafts movement encompasses wallpaper, textile, and furniture design, and the Kelmscott Press's revival of fine book printing, covering decorative fabrics, wood, interior design, and printing arts."
    },
    {
      "episodeTitle": "Vase-mania",
      "pid": "m00268hz",
      "relevantPathsAI": [
        "A",
        "B.1",
        "C.3"
      ],
      "rationaleAI": "Vase-mania covers Josiah Wedgwood's ceramic imitations (Jasperware), the vase as decorative motif in architecture and interior design, directly addressing clay-based decorative arts and the history of taste."
    },
    {
      "episodeTitle": "Automata",
      "pid": "b0bk1c4d",
      "relevantPathsAI": [
        "C.5.c"
      ],
      "rationaleAI": "Automata from Hero of Alexandria through Vaucanson and Jacquet-Droz are decorative mechanical objects par excellence, directly matching the outline's category of automata design."
    },
    {
      "episodeTitle": "The Great Exhibition of 1851",
      "pid": "p003c19x",
      "relevantPathsAI": [
        "A",
        "C.2",
        "C.4.e"
      ],
      "rationaleAI": "The Great Exhibition of 1851 showcased manufactured goods and design reform, directly relevant to industrial design, exhibition design, and the intersection of decorative arts with industrial production."
    },
    {
      "episodeTitle": "The Grand Tour",
      "pid": "p00548fs",
      "relevantPathsAI": [
        "A",
        "C.3"
      ],
      "rationaleAI": "The Grand Tour's influence on British taste, art collecting, connoisseurship, and Neoclassical interior design connects directly to the decorative arts and interior design traditions."
    },
    {
      "episodeTitle": "The Safavid Dynasty",
      "pid": "b0196tcr",
      "relevantPathsAI": [
        "B.2",
        "B.4"
      ],
      "rationaleAI": "Safavid artistic flourishing in carpets and miniatures represents major traditions in decorative fabric arts and glass/ceramic decoration."
    },
    {
      "episodeTitle": "Zen",
      "pid": "b04sxv29",
      "relevantPathsAI": [
        "A"
      ],
      "rationaleAI": "Zen Buddhism's influence on Japanese tea ceremony, calligraphy, and garden design represents a distinctive aesthetic tradition in decorative and functional arts."
    },
    {
      "episodeTitle": "The Vienna Secession",
      "pid": "m002d1b5",
      "relevantPathsAI": [
        "A",
        "C.2.a",
        "C.3"
      ],
      "rationaleAI": "The Vienna Secession and Wiener Werkstatte (Vienna Workshops) represent Art Nouveau applied to decorative arts and functional design, bridging fine art with interior decoration and industrial design."
    }
  ],
  "_curatedBy": "ai",
  "_generatedAt": "2026-03-23"
}
