{
  "_curatedBy": "ai",
  "sectionCode": "131",
  "mappings": [
    {
      "articleTitle": "Science",
      "rationaleAI": "Cosmology is a scientific discipline studying the origin and structure of the universe.",
      "relevantPathsAI": [
        "A.1.c",
        "B.1.a",
        "B.5"
      ]
    },
    {
      "articleTitle": "Astronomy",
      "rationaleAI": "Astronomy provides the observational and theoretical basis for understanding the cosmos and its large-scale structure.",
      "relevantPathsAI": [
        "A.1.b",
        "A.1.d",
        "A.3.c",
        "A.3.e",
        "A.3.f",
        "B.1.a",
        "B.3",
        "C",
        "E.2",
        "E.2.a"
      ]
    },
    {
      "articleTitle": "Solar System",
      "rationaleAI": "The Solar System is part of the Milky Way galaxy and its formation connects to broader cosmological processes.",
      "relevantPathsAI": [
        "A",
        "A.1",
        "A.1.b",
        "A.1.c",
        "A.1.d",
        "A.1.g",
        "A.3",
        "A.3.c",
        "A.3.f",
        "B.1.a"
      ]
    },
    {
      "articleTitle": "Universe",
      "rationaleAI": "The universe, from the Big Bang to its large-scale structure, is the direct subject of cosmological study covered in this section.",
      "relevantPathsAI": [
        "A",
        "A.1",
        "A.1.a",
        "A.1.b",
        "A.1.c",
        "A.1.d",
        "A.1.g",
        "A.2",
        "A.3",
        "A.3.c"
      ]
    },
    {
      "articleTitle": "Nicolaus Copernicus",
      "rationaleAI": "Copernicus proposed the heliocentric model of the cosmos, fundamentally changing humanity's understanding of the universe.",
      "relevantPathsAI": [
        "A",
        "A.1.b",
        "A.1.c",
        "A.1.d",
        "A.3",
        "A.3.c",
        "A.3.f",
        "B.1",
        "B.1.a",
        "B.2.a"
      ]
    },
    {
      "articleTitle": "Galileo Galilei",
      "rationaleAI": "Galileo's observations of Jupiter's moons and planetary phases provided decisive evidence for the heliocentric cosmos.",
      "relevantPathsAI": [
        "A",
        "A.1.b",
        "A.1.c",
        "A.1.d",
        "A.1.g",
        "A.2",
        "A.3",
        "A.3.c",
        "A.3.e",
        "B.1"
      ]
    },
    {
      "articleTitle": "Albert Einstein",
      "rationaleAI": "Einstein's general relativity transformed understanding of the cosmos, spacetime, and gravitation.",
      "relevantPathsAI": [
        "A",
        "A.1",
        "A.1.b",
        "A.1.c",
        "A.1.d",
        "A.2",
        "A.3",
        "A.3.c",
        "B.1",
        "B.1.a"
      ]
    },
    {
      "articleTitle": "Big Bang",
      "rationaleAI": "The Big Bang is the foundational cosmological event describing the origin of the cosmos.",
      "relevantPathsAI": [
        "A",
        "A.1",
        "A.1.a",
        "A.1.b",
        "A.1.c",
        "A.1.d",
        "A.1.e",
        "A.1.f",
        "A.1.g",
        "A.2"
      ]
    },
    {
      "articleTitle": "Black hole",
      "rationaleAI": "Black holes shape the structure and dynamics of the cosmos at large scales.",
      "relevantPathsAI": [
        "A",
        "A.1",
        "A.1.a",
        "A.1.b",
        "A.1.c",
        "A.1.d",
        "A.1.f",
        "A.1.g",
        "A.2",
        "A.3"
      ]
    },
    {
      "articleTitle": "Outer space",
      "rationaleAI": "Outer space is the vast expanse of the cosmos beyond Earth's atmosphere.",
      "relevantPathsAI": [
        "A",
        "A.1.b",
        "A.1.c",
        "A.1.d",
        "A.1.g",
        "A.3",
        "A.3.c",
        "B.1.a",
        "B.3.b",
        "B.4"
      ]
    },
    {
      "articleTitle": "Physical cosmology",
      "rationaleAI": "Physical cosmology studies the origin, structure, and fate of the cosmos treated here.",
      "relevantPathsAI": [
        "A",
        "A.1",
        "A.1.a",
        "A.1.b",
        "A.1.c",
        "A.1.d",
        "A.1.e",
        "A.1.g",
        "A.2",
        "A.3"
      ]
    },
    {
      "articleTitle": "Time",
      "rationaleAI": "Time is a fundamental dimension of the cosmos whose nature is explored in cosmological context.",
      "relevantPathsAI": [
        "A",
        "A.1.b",
        "A.1.c",
        "A.1.d",
        "A.1.g",
        "A.3",
        "A.3.c",
        "B.1.a",
        "B.2",
        "B.3"
      ]
    },
    {
      "articleTitle": "Gravity",
      "rationaleAI": "Gravity shapes the large-scale structure of the cosmos addressed in this section.",
      "relevantPathsAI": [
        "A.1.b",
        "A.3.c",
        "A.3.e",
        "B",
        "B.1",
        "B.1.b",
        "B.2",
        "B.2.a",
        "B.2.b",
        "B.3"
      ]
    },
    {
      "articleTitle": "Space",
      "rationaleAI": "Physical space constitutes the fabric of the cosmos explored in this section.",
      "relevantPathsAI": [
        "A",
        "A.1.b",
        "A.1.c",
        "A.1.d",
        "A.1.g",
        "A.3",
        "A.3.c",
        "B.1.a",
        "B.2",
        "B.3.b"
      ]
    },
    {
      "articleTitle": "Theory of relativity",
      "rationaleAI": "General relativity describes the structure and dynamics of the cosmos at large scales.",
      "relevantPathsAI": [
        "A.1.b",
        "B.1",
        "B.3",
        "B.3.a",
        "B.3.b",
        "D",
        "D.1",
        "D.1.b",
        "D.1.c",
        "D.2"
      ]
    },
    {
      "articleTitle": "Speed of light",
      "rationaleAI": "The speed of light sets the causal structure of the cosmos in relativistic cosmology.",
      "relevantPathsAI": [
        "A",
        "A.1.b",
        "A.1.c",
        "A.1.d",
        "A.1.g",
        "A.3",
        "A.3.c",
        "A.3.f",
        "B.1.a",
        "B.2"
      ]
    }
  ]
}
