{
  "_curatedBy": "ai",
  "sectionCode": "541",
  "mappings": [
    {
      "articleTitle": "Philosophy",
      "rationaleAI": "Political theory has deep roots in philosophical traditions of ethics and governance.",
      "relevantPathsAI": []
    },
    {
      "articleTitle": "Society",
      "rationaleAI": "Political theory addresses the philosophical foundations of societal governance.",
      "relevantPathsAI": [
        "A.4",
        "A.5.a",
        "A.5.b",
        "C.3.a"
      ]
    },
    {
      "articleTitle": "Ethics",
      "rationaleAI": "Ethics provides the moral philosophical foundations that underpin political theory, including questions of justice, rights, and the good society.",
      "relevantPathsAI": [
        "C"
      ]
    },
    {
      "articleTitle": "Government",
      "rationaleAI": "Government is the institutional expression of political theory, embodying ideas about sovereignty, legitimacy, and the common good.",
      "relevantPathsAI": [
        "A.4",
        "A.4.b",
        "A.5",
        "A.5.a",
        "A.5.b",
        "B.4",
        "C",
        "C.3",
        "C.3.a",
        "C.3.b"
      ]
    },
    {
      "articleTitle": "Law",
      "rationaleAI": "Legal systems embody political theory about authority, rights, and justice, linking law to fundamental questions of governance.",
      "relevantPathsAI": [
        "A.4.b",
        "A.5.a",
        "A.5.b",
        "A.5.c",
        "C.3.a",
        "C.4.b",
        "C.4.c"
      ]
    },
    {
      "articleTitle": "Politics",
      "rationaleAI": "Political theory provides the philosophical foundations for understanding political activity, power, and governance.",
      "relevantPathsAI": [
        "A",
        "A.2",
        "A.4",
        "A.4.d",
        "A.5",
        "A.5.a",
        "A.5.b",
        "C",
        "C.1",
        "C.3"
      ]
    },
    {
      "articleTitle": "State (polity)",
      "rationaleAI": "The state as a political entity is a central concept in political theory, from Hobbes's Leviathan to modern theories of sovereignty.",
      "relevantPathsAI": [
        "A",
        "A.2",
        "A.3",
        "A.4",
        "A.4.b",
        "A.4.d",
        "A.5",
        "A.5.a",
        "A.5.b",
        "B"
      ]
    },
    {
      "articleTitle": "Mahatma Gandhi",
      "rationaleAI": "Gandhi's philosophy of nonviolent resistance became a foundational contribution to modern political theory.",
      "relevantPathsAI": [
        "A",
        "A.2",
        "A.4",
        "A.4.b",
        "A.4.d",
        "B.4",
        "C",
        "C.1",
        "C.2",
        "C.3.a"
      ]
    },
    {
      "articleTitle": "Mao Zedong",
      "rationaleAI": "Mao's adaptation of Marxism-Leninism into Maoism constituted a major contribution to 20th-century political theory.",
      "relevantPathsAI": [
        "A",
        "A.2",
        "A.3",
        "A.4",
        "A.4.b",
        "A.4.d",
        "A.5.a",
        "A.5.b",
        "B.4",
        "C"
      ]
    },
    {
      "articleTitle": "Cicero",
      "rationaleAI": "Cicero's works on republicanism, natural law, and justice are foundational texts in Western political theory.",
      "relevantPathsAI": [
        "A",
        "A.2",
        "A.4",
        "A.4.b",
        "A.4.d",
        "B.4",
        "C",
        "C.1",
        "C.3",
        "C.3.a"
      ]
    },
    {
      "articleTitle": "Niccolò Machiavelli",
      "rationaleAI": "Machiavelli's The Prince is a foundational work of modern political theory on power, statecraft, and governance.",
      "relevantPathsAI": [
        "A",
        "A.2",
        "A.4",
        "A.4.a",
        "A.4.b",
        "A.4.d",
        "B.4",
        "C",
        "C.1",
        "C.3.a"
      ]
    },
    {
      "articleTitle": "John Locke",
      "rationaleAI": "Locke's social contract theory and defense of individual rights profoundly influenced modern liberal political theory.",
      "relevantPathsAI": [
        "A",
        "A.2",
        "A.4",
        "A.4.b",
        "A.4.d",
        "A.5.a",
        "A.5.b",
        "B",
        "B.4",
        "C"
      ]
    },
    {
      "articleTitle": "Mary Wollstonecraft",
      "rationaleAI": "Wollstonecraft's A Vindication of the Rights of Woman is a foundational text in feminist political theory.",
      "relevantPathsAI": [
        "A.2",
        "A.4",
        "A.4.b",
        "A.4.d",
        "C.2",
        "C.3.a",
        "C.4.a",
        "C.4.b",
        "C.4.c"
      ]
    },
    {
      "articleTitle": "Karl Marx",
      "rationaleAI": "Marx's theories of class struggle and historical materialism are among the most influential frameworks in modern political theory.",
      "relevantPathsAI": [
        "A",
        "A.2",
        "A.3",
        "A.4",
        "A.4.b",
        "A.4.d",
        "B",
        "B.4",
        "C",
        "C.1"
      ]
    },
    {
      "articleTitle": "Age of Enlightenment",
      "rationaleAI": "Enlightenment thinkers articulated theories of natural rights, social contract, and liberal governance that shaped modern political theory.",
      "relevantPathsAI": [
        "A",
        "A.2",
        "A.3",
        "A.4",
        "A.4.b",
        "A.4.d",
        "A.5",
        "A.5.a",
        "A.5.b",
        "C.3"
      ]
    },
    {
      "articleTitle": "American Revolution",
      "rationaleAI": "The American Revolution put Enlightenment political theories of natural rights and self-governance into practice.",
      "relevantPathsAI": [
        "A",
        "A.2",
        "A.3",
        "A.4",
        "A.4.b",
        "A.4.d",
        "A.5.c",
        "B.4",
        "C",
        "C.1"
      ]
    },
    {
      "articleTitle": "French Revolution",
      "rationaleAI": "The French Revolution enacted Enlightenment ideals of liberty, equality, and popular sovereignty, reshaping political theory.",
      "relevantPathsAI": [
        "A",
        "A.2",
        "A.4",
        "A.4.b",
        "A.4.c",
        "A.4.d",
        "A.5.a",
        "A.5.b",
        "A.5.c",
        "B.4"
      ]
    },
    {
      "articleTitle": "Secularism",
      "rationaleAI": "Secularism is a political theory about the separation of religion and state.",
      "relevantPathsAI": [
        "A",
        "A.2",
        "C",
        "C.3.a",
        "C.3.b",
        "C.4",
        "C.4.a"
      ]
    },
    {
      "articleTitle": "Power (social and political)",
      "rationaleAI": "Power is a central concept in political theory.",
      "relevantPathsAI": [
        "A",
        "A.4",
        "A.4.b",
        "A.5.a",
        "B",
        "B.4",
        "C",
        "C.1",
        "C.3.a",
        "C.3.b"
      ]
    },
    {
      "articleTitle": "Political science",
      "rationaleAI": "Political science studies the theories underlying political systems.",
      "relevantPathsAI": [
        "A.5.a",
        "A.5.c",
        "C",
        "C.3.a",
        "C.3.b",
        "C.4"
      ]
    },
    {
      "articleTitle": "Democracy",
      "rationaleAI": "Democracy is a fundamental concept in political theory.",
      "relevantPathsAI": [
        "A",
        "A.2",
        "A.4",
        "A.4.b",
        "A.4.c",
        "A.5",
        "A.5.a",
        "A.5.b",
        "A.5.c",
        "B.4"
      ]
    },
    {
      "articleTitle": "Dictatorship",
      "rationaleAI": "Dictatorship is a form of political organization addressed in political theory.",
      "relevantPathsAI": [
        "A.4"
      ]
    },
    {
      "articleTitle": "Monarchy",
      "rationaleAI": "Monarchy is a fundamental concept in political theory.",
      "relevantPathsAI": [
        "A",
        "A.2",
        "A.3",
        "A.4",
        "A.4.b",
        "A.4.c",
        "A.4.d",
        "A.5.a",
        "A.5.b",
        "A.5.c"
      ]
    },
    {
      "articleTitle": "Ideology",
      "rationaleAI": "Ideology provides the theoretical frameworks underlying political systems.",
      "relevantPathsAI": [
        "A",
        "A.2",
        "A.3",
        "A.4",
        "A.4.b",
        "A.4.d",
        "B",
        "B.4",
        "C",
        "C.1"
      ]
    },
    {
      "articleTitle": "Anarchism",
      "rationaleAI": "Anarchism is a political theory opposing state authority.",
      "relevantPathsAI": [
        "A",
        "A.2",
        "A.3",
        "A.4",
        "A.4.b",
        "A.4.d",
        "A.5",
        "A.5.a",
        "B.4",
        "C"
      ]
    },
    {
      "articleTitle": "Capitalism",
      "rationaleAI": "Capitalism has political theoretical dimensions regarding state and market.",
      "relevantPathsAI": [
        "A",
        "A.2",
        "A.4",
        "A.4.b",
        "A.5.a",
        "A.5.b",
        "A.5.c",
        "C",
        "C.3",
        "C.3.a"
      ]
    },
    {
      "articleTitle": "Communism",
      "rationaleAI": "Communism is a major political theory.",
      "relevantPathsAI": [
        "A",
        "A.2",
        "A.3",
        "A.4",
        "A.4.b",
        "A.4.d",
        "B",
        "B.4",
        "C",
        "C.1"
      ]
    },
    {
      "articleTitle": "Conservatism",
      "rationaleAI": "Conservatism is a major political theory.",
      "relevantPathsAI": [
        "A",
        "A.2",
        "A.3",
        "A.4",
        "A.4.b",
        "A.4.d",
        "A.5.a",
        "C",
        "C.3",
        "C.3.a"
      ]
    },
    {
      "articleTitle": "Fascism",
      "rationaleAI": "Fascism is a political theory and ideology.",
      "relevantPathsAI": [
        "A",
        "A.2",
        "A.3",
        "A.4",
        "A.4.a",
        "A.4.b",
        "A.4.d",
        "B",
        "B.1",
        "B.2"
      ]
    },
    {
      "articleTitle": "Liberalism",
      "rationaleAI": "Liberalism is a foundational political theory.",
      "relevantPathsAI": [
        "A",
        "A.2",
        "A.4.b",
        "A.4.d",
        "A.5",
        "A.5.a",
        "B",
        "B.1",
        "B.3",
        "C"
      ]
    },
    {
      "articleTitle": "Nationalism",
      "rationaleAI": "Nationalism is a major political theory.",
      "relevantPathsAI": [
        "A",
        "A.2",
        "A.3",
        "A.4",
        "A.4.b",
        "A.4.d",
        "A.5.a",
        "B.4",
        "C",
        "C.1"
      ]
    },
    {
      "articleTitle": "Socialism",
      "rationaleAI": "Socialism is a major political and economic theory.",
      "relevantPathsAI": [
        "A",
        "A.2",
        "A.3",
        "A.4",
        "A.4.b",
        "A.4.d",
        "B",
        "B.4",
        "C",
        "C.1"
      ]
    },
    {
      "articleTitle": "Nation",
      "rationaleAI": "The concept of nationhood is central to political theory.",
      "relevantPathsAI": [
        "A",
        "A.2",
        "A.4",
        "A.4.b",
        "A.4.d",
        "B.1",
        "B.4",
        "C",
        "C.1",
        "C.3"
      ]
    },
    {
      "articleTitle": "Discrimination",
      "rationaleAI": "Anti-discrimination principles are central to political theory.",
      "relevantPathsAI": [
        "A",
        "A.2",
        "A.3",
        "A.4.b",
        "A.5.a",
        "C",
        "C.4.a",
        "C.4.c"
      ]
    },
    {
      "articleTitle": "Feminism",
      "rationaleAI": "Feminism is a political theory addressing gender equality.",
      "relevantPathsAI": [
        "A.4.b",
        "A.5",
        "A.5.a",
        "C",
        "C.3",
        "C.3.a",
        "C.3.b",
        "C.3.i.iv",
        "C.3.v.viii"
      ]
    },
    {
      "articleTitle": "Human rights",
      "rationaleAI": "Human rights are central to political theory.",
      "relevantPathsAI": [
        "A",
        "A.1",
        "A.2",
        "A.3",
        "A.4",
        "A.4.a",
        "A.4.b",
        "A.4.d",
        "A.5.a",
        "C"
      ]
    },
    {
      "articleTitle": "Liberty",
      "rationaleAI": "Liberty is a foundational concept in political theory.",
      "relevantPathsAI": [
        "A",
        "A.2",
        "A.4.b",
        "A.5.a",
        "B",
        "C",
        "C.1",
        "C.3",
        "C.3.a",
        "C.3.b"
      ]
    },
    {
      "articleTitle": "Privacy",
      "rationaleAI": "Privacy is a political concept related to individual rights.",
      "relevantPathsAI": [
        "A",
        "A.2",
        "A.3",
        "A.4",
        "A.4.b",
        "A.4.d",
        "A.5.a",
        "A.5.b",
        "A.5.c",
        "C.2"
      ]
    },
    {
      "articleTitle": "Social equality",
      "rationaleAI": "Equality is a foundational concept in political theory.",
      "relevantPathsAI": [
        "A.4.b"
      ]
    }
  ]
}
