{
  "_curatedBy": "ai",
  "sectionCode": "621",
  "mappings": [
    {
      "articleTitle": "The arts",
      "rationaleAI": "Literature is one of the major creative arts covered by this foundational article on artistic expression.",
      "relevantPathsAI": [
        "A",
        "A.1",
        "A.2",
        "A.5",
        "A.6",
        "B.1",
        "B.1.b",
        "B.2",
        "B.2.b",
        "C"
      ]
    },
    {
      "articleTitle": "Literature",
      "rationaleAI": "Literature is the direct subject of this section covering novels, poetry, drama, and other written art forms.",
      "relevantPathsAI": [
        "A",
        "A.1",
        "A.2",
        "A.3",
        "A.4",
        "A.5",
        "A.7",
        "B",
        "B.1.b",
        "B.2"
      ]
    },
    {
      "articleTitle": "Writing",
      "rationaleAI": "Written literature depends on writing systems, and the evolution of script directly shaped literary forms and traditions.",
      "relevantPathsAI": [
        "A",
        "A.1",
        "A.5",
        "A.7",
        "B.1.b",
        "B.2",
        "B.2.b",
        "C.2.b",
        "C.2.c",
        "C.2.d"
      ]
    },
    {
      "articleTitle": "Folklore",
      "rationaleAI": "Oral literature including epics, folktales, and ballads represents a foundational literary tradition predating written literature.",
      "relevantPathsAI": [
        "A",
        "A.1",
        "A.4",
        "B.1.b",
        "B.2",
        "B.2.b",
        "C.2.b",
        "C.2.c",
        "C.2.d",
        "C.2.e"
      ]
    },
    {
      "articleTitle": "Homer",
      "rationaleAI": "Homer's Iliad and Odyssey are the foundational works of Western literature.",
      "relevantPathsAI": [
        "A",
        "A.1",
        "B.1.b",
        "B.2",
        "B.2.b",
        "C.2.a",
        "C.2.b",
        "C.2.c",
        "C.2.d",
        "C.2.e"
      ]
    },
    {
      "articleTitle": "Virgil",
      "rationaleAI": "Virgil's Aeneid is one of the greatest works of Latin literature and Western literary tradition.",
      "relevantPathsAI": [
        "A",
        "A.1",
        "B.1.b",
        "B.2",
        "B.2.b",
        "C.2.a",
        "C.2.b",
        "C.2.c",
        "C.2.d",
        "C.2.e"
      ]
    },
    {
      "articleTitle": "Li Bai",
      "rationaleAI": "Li Bai is regarded as one of the greatest poets in Chinese literary history.",
      "relevantPathsAI": [
        "A",
        "A.1",
        "A.5",
        "B.1.b",
        "B.2",
        "B.2.i",
        "B.2.b",
        "C.2.b",
        "C.2.c",
        "C.2.d"
      ]
    },
    {
      "articleTitle": "Murasaki Shikibu",
      "rationaleAI": "Murasaki Shikibu's The Tale of Genji is often considered the world's first novel and a masterpiece of Japanese literature.",
      "relevantPathsAI": [
        "A",
        "A.1",
        "B.1.b",
        "B.2",
        "B.2.b",
        "C.1",
        "C.2.b",
        "C.2.c",
        "C.2.d",
        "C.2.e"
      ]
    },
    {
      "articleTitle": "Rumi",
      "rationaleAI": "Rumi is one of the most widely read poets in the world and a towering figure of Persian literature.",
      "relevantPathsAI": [
        "A",
        "A.1",
        "A.3",
        "A.4",
        "A.5",
        "A.7",
        "B",
        "B.1.b",
        "B.2",
        "B.2.b"
      ]
    },
    {
      "articleTitle": "Dante Alighieri",
      "rationaleAI": "Dante's Divine Comedy is one of the greatest masterworks of world literature.",
      "relevantPathsAI": [
        "A",
        "A.1",
        "B.1.b",
        "B.2",
        "B.2.b",
        "C.1",
        "C.2.a",
        "C.2.b",
        "C.2.c",
        "C.2.d"
      ]
    },
    {
      "articleTitle": "William Shakespeare",
      "rationaleAI": "Shakespeare is widely regarded as the greatest writer in the English language and the world's foremost dramatist.",
      "relevantPathsAI": [
        "A",
        "A.1",
        "A.7",
        "B.1.b",
        "B.2",
        "B.2.b",
        "C.2.b",
        "C.2.c",
        "C.2.d",
        "C.2.e"
      ]
    },
    {
      "articleTitle": "Voltaire",
      "rationaleAI": "Voltaire was one of the most prolific and influential writers of the Enlightenment era.",
      "relevantPathsAI": [
        "A",
        "A.1",
        "A.7",
        "B.1.b",
        "B.2",
        "B.2.b",
        "C.1",
        "C.2.b",
        "C.2.c",
        "C.2.d"
      ]
    },
    {
      "articleTitle": "Leo Tolstoy",
      "rationaleAI": "Tolstoy's War and Peace and Anna Karenina are among the greatest novels in world literature.",
      "relevantPathsAI": [
        "A",
        "A.1",
        "A.5",
        "A.7",
        "B.1",
        "B.1.b",
        "B.2",
        "B.2.b",
        "C.2.b",
        "C.2.c"
      ]
    },
    {
      "articleTitle": "Rabindranath Tagore",
      "rationaleAI": "Tagore was the first non-European Nobel laureate in literature and a towering figure of Bengali and world literature.",
      "relevantPathsAI": [
        "A",
        "B.2.b",
        "C.1",
        "C.2.d",
        "C.2.e",
        "C.3.f",
        "C.6.j",
        "C.6.l",
        "C.6.o",
        "C.8"
      ]
    },
    {
      "articleTitle": "History of literature",
      "rationaleAI": "The history of literature traces the evolution of literary forms, traditions, and masterworks.",
      "relevantPathsAI": [
        "A",
        "A.1",
        "A.4",
        "A.7",
        "B",
        "B.2",
        "C.2",
        "C.3",
        "C.4",
        "C.6"
      ]
    },
    {
      "articleTitle": "Tang dynasty",
      "rationaleAI": "Tang-era poetry by Li Bai and Du Fu represents a pinnacle of world literature.",
      "relevantPathsAI": [
        "A",
        "A.1",
        "A.3",
        "A.4",
        "A.5",
        "A.7",
        "B",
        "B.1.b",
        "B.2",
        "B.2.b"
      ]
    },
    {
      "articleTitle": "Modernism",
      "rationaleAI": "Modernism profoundly reshaped literary forms and techniques.",
      "relevantPathsAI": [
        "A",
        "A.1",
        "A.5",
        "B.1",
        "B.1.b",
        "B.2",
        "B.2.b",
        "C.2.b",
        "C.2.c",
        "C.2.d"
      ]
    },
    {
      "articleTitle": "Realism (arts)",
      "rationaleAI": "Literary realism was a dominant movement in 19th-century fiction.",
      "relevantPathsAI": [
        "A",
        "A.1",
        "A.3",
        "A.5",
        "B",
        "B.2",
        "C.2",
        "C.3",
        "C.4",
        "C.6"
      ]
    },
    {
      "articleTitle": "Fiction",
      "rationaleAI": "Fiction is a primary form of literature.",
      "relevantPathsAI": [
        "A.1",
        "A.2",
        "A.6",
        "A.7",
        "B.1.b",
        "B.2",
        "B.2.a",
        "C",
        "C.6.k"
      ]
    },
    {
      "articleTitle": "Novel",
      "rationaleAI": "The novel is a major literary form within the art of literature.",
      "relevantPathsAI": [
        "A",
        "A.1",
        "A.2",
        "A.3",
        "A.4",
        "A.5",
        "A.6",
        "A.7",
        "B",
        "B.1.b"
      ]
    },
    {
      "articleTitle": "Short story",
      "rationaleAI": "The short story is a distinct literary form within literature.",
      "relevantPathsAI": [
        "A.1",
        "A.2",
        "B.1.b",
        "C",
        "C.2.b",
        "C.2.e",
        "C.2.f",
        "C.3.d",
        "C.6.j",
        "C.6.k"
      ]
    },
    {
      "articleTitle": "Non-fiction",
      "rationaleAI": "Non-fiction encompasses literary forms such as essay, biography, and history writing.",
      "relevantPathsAI": []
    },
    {
      "articleTitle": "Poetry",
      "rationaleAI": "Poetry is one of the oldest and most fundamental forms of literature.",
      "relevantPathsAI": [
        "A.1",
        "A.6",
        "B.1.b",
        "B.2",
        "B.2.a",
        "B.2.i",
        "B.2.i.ii",
        "B.2.b",
        "C.1",
        "C.2"
      ]
    },
    {
      "articleTitle": "Comics",
      "rationaleAI": "Comics are a narrative form with literary qualities.",
      "relevantPathsAI": [
        "A.1",
        "B.2",
        "C.2",
        "C.2.b",
        "C.2.f",
        "C.3.d",
        "C.6.j",
        "C.6.m",
        "C.6.o",
        "C.8"
      ]
    },
    {
      "articleTitle": "Greek mythology",
      "rationaleAI": "Greek myths are foundational texts in Western literature.",
      "relevantPathsAI": [
        "A",
        "A.1",
        "A.2",
        "A.3",
        "A.4",
        "A.5",
        "A.7",
        "B",
        "B.1",
        "B.1.b"
      ]
    },
    {
      "articleTitle": "Bible",
      "rationaleAI": "The Bible is one of the most influential works of literature in human history.",
      "relevantPathsAI": [
        "A",
        "A.1",
        "A.3",
        "A.4",
        "A.5",
        "A.7",
        "B",
        "B.1.b",
        "B.2",
        "B.2.b"
      ]
    },
    {
      "articleTitle": "Quran",
      "rationaleAI": "The Quran is one of the most influential works of literature in human history.",
      "relevantPathsAI": [
        "A",
        "A.1",
        "A.2",
        "A.3",
        "A.4",
        "A.5",
        "A.7",
        "B",
        "B.1.b",
        "B.2"
      ]
    },
    {
      "articleTitle": "Bhagavad Gita",
      "rationaleAI": "The Bhagavad Gita is a major work of world literature.",
      "relevantPathsAI": [
        "A",
        "A.1",
        "A.3",
        "A.4",
        "A.5",
        "A.6",
        "A.7",
        "B",
        "B.1.b",
        "B.2"
      ]
    },
    {
      "articleTitle": "Oral tradition",
      "rationaleAI": "Oral tradition is the origin of literary forms.",
      "relevantPathsAI": [
        "C.1"
      ]
    }
  ]
}
