{
  "divisionId": "9-06",
  "readings": {
    "vsi": [
      {
        "title": "Empire",
        "count": 11,
        "paths": 11,
        "author": "Stephen Howe",
        "relevance": 100
      },
      {
        "title": "Nationalism",
        "count": 9,
        "paths": 12,
        "author": "Steven Grosby",
        "relevance": 82
      },
      {
        "title": "Diplomacy",
        "count": 7,
        "paths": 10,
        "author": "Joseph M. Siracusa",
        "relevance": 64
      },
      {
        "title": "Capitalism",
        "count": 6,
        "paths": 10,
        "author": "James Fulcher",
        "relevance": 55
      },
      {
        "title": "Global Economic History",
        "count": 6,
        "paths": 8,
        "author": "Robert C. Allen",
        "relevance": 55
      },
      {
        "title": "Postcolonialism",
        "count": 6,
        "paths": 8,
        "author": "Robert J.C. Young",
        "relevance": 55
      },
      {
        "title": "The British Empire",
        "count": 6,
        "paths": 8,
        "author": "Ashley Jackson",
        "relevance": 55
      },
      {
        "title": "Exploration",
        "count": 5,
        "paths": 7,
        "author": "Stewart A. Weaver",
        "relevance": 45
      },
      {
        "title": "The First World War",
        "count": 5,
        "paths": 6,
        "author": "Michael Howard",
        "relevance": 45
      },
      {
        "title": "Decolonization",
        "count": 5,
        "paths": 5,
        "author": "Dane Kennedy",
        "relevance": 45
      },
      {
        "title": "The Industrial Revolution",
        "count": 4,
        "paths": 7,
        "author": "Robert C. Allen",
        "relevance": 36
      },
      {
        "title": "Islam",
        "count": 4,
        "paths": 6,
        "author": "Malise Ruthven",
        "relevance": 36
      },
      {
        "title": "Democracy",
        "count": 4,
        "paths": 5,
        "author": "Bernard Crick",
        "relevance": 36
      },
      {
        "title": "Modern France",
        "count": 3,
        "paths": 6,
        "author": "Vanessa R. Schwartz",
        "relevance": 27
      },
      {
        "title": "American Slavery",
        "count": 3,
        "paths": 5,
        "author": "Heather Andrea Williams",
        "relevance": 27
      },
      {
        "title": "Revolutions",
        "count": 3,
        "paths": 5,
        "author": "Jack A. Goldstone",
        "relevance": 27
      },
      {
        "title": "The Catholic Reformation",
        "count": 3,
        "paths": 5,
        "author": "James E. Kelly",
        "relevance": 27
      },
      {
        "title": "The Habsburg Empire",
        "count": 3,
        "paths": 5,
        "author": "Martyn Rady",
        "relevance": 27
      },
      {
        "title": "Russian History",
        "count": 3,
        "paths": 4,
        "author": "Geoffrey Hosking",
        "relevance": 27
      },
      {
        "title": "The French Revolution",
        "count": 3,
        "paths": 3,
        "author": "William Doyle",
        "relevance": 27
      },
      {
        "title": "Abolitionism",
        "count": 2,
        "paths": 4,
        "author": "Richard S. Newman",
        "relevance": 18
      },
      {
        "title": "Aristocracy",
        "count": 2,
        "paths": 4,
        "author": "William Doyle",
        "relevance": 18
      },
      {
        "title": "Diaspora",
        "count": 2,
        "paths": 4,
        "author": "Kevin Kenny",
        "relevance": 18
      },
      {
        "title": "Global Islam",
        "count": 2,
        "paths": 4,
        "author": "Nile Green",
        "relevance": 18
      },
      {
        "title": "North American Indians",
        "count": 2,
        "paths": 4,
        "author": "Theda Perdue, Michael D. Green",
        "relevance": 18
      },
      {
        "title": "Scotland",
        "count": 2,
        "paths": 4,
        "author": "Rab Houston",
        "relevance": 18
      },
      {
        "title": "American Immigration",
        "count": 2,
        "paths": 3,
        "author": "David A. Gerber",
        "relevance": 18
      },
      {
        "title": "Buddhism",
        "count": 2,
        "paths": 3,
        "author": "Damien Keown",
        "relevance": 18
      },
      {
        "title": "Islamic History",
        "count": 2,
        "paths": 3,
        "author": "Adam J. Silverstein",
        "relevance": 18
      },
      {
        "title": "Modern Ireland",
        "count": 2,
        "paths": 3,
        "author": "Senia Paseta",
        "relevance": 18
      },
      {
        "title": "Napoleon",
        "count": 2,
        "paths": 3,
        "author": "David A. Bell",
        "relevance": 18
      },
      {
        "title": "Socialism",
        "count": 2,
        "paths": 3,
        "author": "Michael Newman",
        "relevance": 18
      },
      {
        "title": "The Holy Roman Empire",
        "count": 2,
        "paths": 3,
        "author": "Joachim Whaley",
        "relevance": 18
      },
      {
        "title": "The Mexican Revolution",
        "count": 2,
        "paths": 3,
        "author": "Alan Knight",
        "relevance": 18
      },
      {
        "title": "Tocqueville",
        "count": 2,
        "paths": 3,
        "author": "Harvey Mansfield",
        "relevance": 18
      },
      {
        "title": "Zionism",
        "count": 2,
        "paths": 3,
        "author": "Michael Stanislawski",
        "relevance": 18
      },
      {
        "title": "Colonial Latin American Literature",
        "count": 2,
        "paths": 2,
        "author": "Rolena Adorno",
        "relevance": 18
      },
      {
        "title": "Eighteenth-Century Britain",
        "count": 2,
        "paths": 2,
        "author": "Paul Langford",
        "relevance": 18
      },
      {
        "title": "Iran",
        "count": 2,
        "paths": 2,
        "author": "Ali Ansari",
        "relevance": 18
      },
      {
        "title": "Kant",
        "count": 2,
        "paths": 2,
        "author": "Roger Scruton",
        "relevance": 18
      },
      {
        "title": "Modern Brazil",
        "count": 2,
        "paths": 2,
        "author": "Anthony W. Pereira",
        "relevance": 18
      },
      {
        "title": "Navigation",
        "count": 2,
        "paths": 2,
        "author": "Jim Bennett",
        "relevance": 18
      },
      {
        "title": "Puritanism",
        "count": 2,
        "paths": 2,
        "author": "Francis J. Bremer",
        "relevance": 18
      },
      {
        "title": "The American Revolution",
        "count": 2,
        "paths": 2,
        "author": "Robert J. Allison",
        "relevance": 18
      },
      {
        "title": "The Conquistadors",
        "count": 2,
        "paths": 2,
        "author": "Matthew Restall, Felipe Fernández-Armesto",
        "relevance": 18
      },
      {
        "title": "The Enlightenment",
        "count": 2,
        "paths": 2,
        "author": "John Robertson",
        "relevance": 18
      },
      {
        "title": "The Founding Fathers",
        "count": 2,
        "paths": 2,
        "author": "Richard B. Bernstein",
        "relevance": 18
      },
      {
        "title": "The Napoleonic Wars",
        "count": 2,
        "paths": 2,
        "author": "Mike Rapport",
        "relevance": 18
      },
      {
        "title": "The Treaty of Versailles",
        "count": 2,
        "paths": 2,
        "author": "Michael S. Neiberg",
        "relevance": 18
      }
    ],
    "wiki": [
      {
        "title": "British Empire",
        "count": 10,
        "paths": 43,
        "relevance": 100
      },
      {
        "title": "Imperialism",
        "count": 10,
        "paths": 23,
        "relevance": 100
      },
      {
        "title": "Colonialism",
        "count": 8,
        "paths": 23,
        "relevance": 80
      },
      {
        "title": "Spain",
        "count": 7,
        "paths": 20,
        "relevance": 70
      },
      {
        "title": "Atlantic slave trade",
        "count": 6,
        "paths": 14,
        "relevance": 60
      },
      {
        "title": "Age of Enlightenment",
        "count": 6,
        "paths": 10,
        "relevance": 60
      },
      {
        "title": "Spanish Empire",
        "count": 5,
        "paths": 28,
        "relevance": 50
      },
      {
        "title": "United States",
        "count": 5,
        "paths": 15,
        "relevance": 50
      },
      {
        "title": "France",
        "count": 5,
        "paths": 12,
        "relevance": 50
      },
      {
        "title": "Age of Discovery",
        "count": 5,
        "paths": 11,
        "relevance": 50
      },
      {
        "title": "American Revolution",
        "count": 5,
        "paths": 6,
        "relevance": 50
      },
      {
        "title": "Ottoman Empire",
        "count": 4,
        "paths": 17,
        "relevance": 40
      },
      {
        "title": "World War I",
        "count": 4,
        "paths": 12,
        "relevance": 40
      },
      {
        "title": "Russia",
        "count": 4,
        "paths": 11,
        "relevance": 40
      },
      {
        "title": "Early modern period",
        "count": 4,
        "paths": 8,
        "relevance": 40
      },
      {
        "title": "George Washington",
        "count": 4,
        "paths": 7,
        "relevance": 40
      },
      {
        "title": "Napoleon",
        "count": 4,
        "paths": 7,
        "relevance": 40
      },
      {
        "title": "Reformation",
        "count": 4,
        "paths": 7,
        "relevance": 40
      },
      {
        "title": "Mexico",
        "count": 3,
        "paths": 18,
        "relevance": 30
      },
      {
        "title": "China",
        "count": 3,
        "paths": 13,
        "relevance": 30
      },
      {
        "title": "Poland",
        "count": 3,
        "paths": 11,
        "relevance": 30
      },
      {
        "title": "Mughal Empire",
        "count": 3,
        "paths": 9,
        "relevance": 30
      },
      {
        "title": "United Kingdom",
        "count": 3,
        "paths": 7,
        "relevance": 30
      },
      {
        "title": "Italy",
        "count": 3,
        "paths": 6,
        "relevance": 30
      },
      {
        "title": "Holy Roman Empire",
        "count": 3,
        "paths": 5,
        "relevance": 30
      },
      {
        "title": "John Locke",
        "count": 3,
        "paths": 4,
        "relevance": 30
      },
      {
        "title": "Brazil",
        "count": 2,
        "paths": 10,
        "relevance": 20
      },
      {
        "title": "Canada",
        "count": 2,
        "paths": 10,
        "relevance": 20
      },
      {
        "title": "South America",
        "count": 2,
        "paths": 10,
        "relevance": 20
      },
      {
        "title": "North America",
        "count": 2,
        "paths": 8,
        "relevance": 20
      },
      {
        "title": "Scramble for Africa",
        "count": 2,
        "paths": 8,
        "relevance": 20
      },
      {
        "title": "Argentina",
        "count": 2,
        "paths": 7,
        "relevance": 20
      },
      {
        "title": "History of Asia",
        "count": 2,
        "paths": 7,
        "relevance": 20
      },
      {
        "title": "Colombia",
        "count": 2,
        "paths": 6,
        "relevance": 20
      },
      {
        "title": "Europe",
        "count": 2,
        "paths": 5,
        "relevance": 20
      },
      {
        "title": "Karl Marx",
        "count": 2,
        "paths": 5,
        "relevance": 20
      },
      {
        "title": "Egypt",
        "count": 2,
        "paths": 4,
        "relevance": 20
      },
      {
        "title": "Mesoamerica",
        "count": 2,
        "paths": 4,
        "relevance": 20
      },
      {
        "title": "Renaissance",
        "count": 2,
        "paths": 4,
        "relevance": 20
      },
      {
        "title": "Catherine the Great",
        "count": 2,
        "paths": 3,
        "relevance": 20
      },
      {
        "title": "Christopher Columbus",
        "count": 2,
        "paths": 3,
        "relevance": 20
      },
      {
        "title": "Elizabeth I",
        "count": 2,
        "paths": 3,
        "relevance": 20
      },
      {
        "title": "Industrial Revolution",
        "count": 2,
        "paths": 3,
        "relevance": 20
      },
      {
        "title": "Rocky Mountains",
        "count": 2,
        "paths": 3,
        "relevance": 20
      },
      {
        "title": "Suleiman the Magnificent",
        "count": 2,
        "paths": 3,
        "relevance": 20
      },
      {
        "title": "Philippines",
        "count": 2,
        "paths": 2,
        "relevance": 20
      },
      {
        "title": "Turkey",
        "count": 2,
        "paths": 2,
        "relevance": 20
      }
    ],
    "macro": [
      {
        "title": "Asia",
        "count": 5,
        "paths": 5,
        "relevance": 100
      },
      {
        "title": "Austria",
        "count": 3,
        "paths": 3,
        "relevance": 60
      },
      {
        "title": "Balkan States",
        "count": 3,
        "paths": 3,
        "relevance": 60
      },
      {
        "title": "Czech and Slovak Republics",
        "count": 3,
        "paths": 3,
        "relevance": 60
      },
      {
        "title": "European History and Culture",
        "count": 3,
        "paths": 3,
        "relevance": 60
      },
      {
        "title": "Hungary",
        "count": 3,
        "paths": 3,
        "relevance": 60
      },
      {
        "title": "North America",
        "count": 3,
        "paths": 3,
        "relevance": 60
      },
      {
        "title": "Afghanistan",
        "count": 2,
        "paths": 2,
        "relevance": 40
      },
      {
        "title": "Africa",
        "count": 2,
        "paths": 2,
        "relevance": 40
      },
      {
        "title": "Amsterdam",
        "count": 2,
        "paths": 2,
        "relevance": 40
      },
      {
        "title": "Arabia",
        "count": 2,
        "paths": 2,
        "relevance": 40
      },
      {
        "title": "Arctic, The",
        "count": 2,
        "paths": 2,
        "relevance": 40
      },
      {
        "title": "Athens",
        "count": 2,
        "paths": 2,
        "relevance": 40
      },
      {
        "title": "Baltic States",
        "count": 2,
        "paths": 2,
        "relevance": 40
      },
      {
        "title": "Barcelona",
        "count": 2,
        "paths": 2,
        "relevance": 40
      },
      {
        "title": "Belarus",
        "count": 2,
        "paths": 2,
        "relevance": 40
      },
      {
        "title": "Belgium",
        "count": 2,
        "paths": 2,
        "relevance": 40
      },
      {
        "title": "Berlin",
        "count": 2,
        "paths": 2,
        "relevance": 40
      },
      {
        "title": "Boston",
        "count": 2,
        "paths": 2,
        "relevance": 40
      },
      {
        "title": "Budapest",
        "count": 2,
        "paths": 2,
        "relevance": 40
      },
      {
        "title": "Canada",
        "count": 2,
        "paths": 2,
        "relevance": 40
      },
      {
        "title": "Cologne",
        "count": 2,
        "paths": 2,
        "relevance": 40
      },
      {
        "title": "Columbus",
        "count": 2,
        "paths": 2,
        "relevance": 40
      },
      {
        "title": "Denmark",
        "count": 2,
        "paths": 2,
        "relevance": 40
      },
      {
        "title": "Dublin",
        "count": 2,
        "paths": 2,
        "relevance": 40
      },
      {
        "title": "Edinburgh",
        "count": 2,
        "paths": 2,
        "relevance": 40
      },
      {
        "title": "Egypt",
        "count": 2,
        "paths": 2,
        "relevance": 40
      },
      {
        "title": "Finland",
        "count": 2,
        "paths": 2,
        "relevance": 40
      },
      {
        "title": "Florence",
        "count": 2,
        "paths": 2,
        "relevance": 40
      },
      {
        "title": "France",
        "count": 2,
        "paths": 2,
        "relevance": 40
      },
      {
        "title": "Geneva",
        "count": 2,
        "paths": 2,
        "relevance": 40
      },
      {
        "title": "Germany",
        "count": 2,
        "paths": 2,
        "relevance": 40
      },
      {
        "title": "Greece",
        "count": 2,
        "paths": 2,
        "relevance": 40
      },
      {
        "title": "Hamburg",
        "count": 2,
        "paths": 2,
        "relevance": 40
      },
      {
        "title": "Iceland",
        "count": 2,
        "paths": 2,
        "relevance": 40
      },
      {
        "title": "Iran",
        "count": 2,
        "paths": 2,
        "relevance": 40
      },
      {
        "title": "Ireland",
        "count": 2,
        "paths": 2,
        "relevance": 40
      },
      {
        "title": "Italy",
        "count": 2,
        "paths": 2,
        "relevance": 40
      },
      {
        "title": "Latin America, The History of",
        "count": 2,
        "paths": 2,
        "relevance": 40
      },
      {
        "title": "Lebanon",
        "count": 2,
        "paths": 2,
        "relevance": 40
      },
      {
        "title": "Lisbon",
        "count": 2,
        "paths": 2,
        "relevance": 40
      },
      {
        "title": "London",
        "count": 2,
        "paths": 2,
        "relevance": 40
      },
      {
        "title": "Luxembourg",
        "count": 2,
        "paths": 2,
        "relevance": 40
      },
      {
        "title": "Madrid",
        "count": 2,
        "paths": 2,
        "relevance": 40
      },
      {
        "title": "Malta",
        "count": 2,
        "paths": 2,
        "relevance": 40
      },
      {
        "title": "Manchester",
        "count": 2,
        "paths": 2,
        "relevance": 40
      },
      {
        "title": "Marseille",
        "count": 2,
        "paths": 2,
        "relevance": 40
      },
      {
        "title": "Mexico",
        "count": 2,
        "paths": 2,
        "relevance": 40
      },
      {
        "title": "Milan",
        "count": 2,
        "paths": 2,
        "relevance": 40
      },
      {
        "title": "Montreal",
        "count": 2,
        "paths": 2,
        "relevance": 40
      },
      {
        "title": "Moscow",
        "count": 2,
        "paths": 2,
        "relevance": 40
      },
      {
        "title": "Naples",
        "count": 2,
        "paths": 2,
        "relevance": 40
      },
      {
        "title": "Netherlands, The",
        "count": 2,
        "paths": 2,
        "relevance": 40
      },
      {
        "title": "New Orleans",
        "count": 2,
        "paths": 2,
        "relevance": 40
      },
      {
        "title": "New York City",
        "count": 2,
        "paths": 2,
        "relevance": 40
      },
      {
        "title": "North Africa",
        "count": 2,
        "paths": 2,
        "relevance": 40
      },
      {
        "title": "Norway",
        "count": 2,
        "paths": 2,
        "relevance": 40
      },
      {
        "title": "Palestine",
        "count": 2,
        "paths": 2,
        "relevance": 40
      },
      {
        "title": "Paris",
        "count": 2,
        "paths": 2,
        "relevance": 40
      },
      {
        "title": "Philadelphia",
        "count": 2,
        "paths": 2,
        "relevance": 40
      },
      {
        "title": "Poland",
        "count": 2,
        "paths": 2,
        "relevance": 40
      },
      {
        "title": "Portugal",
        "count": 2,
        "paths": 2,
        "relevance": 40
      },
      {
        "title": "Prague",
        "count": 2,
        "paths": 2,
        "relevance": 40
      },
      {
        "title": "Rome",
        "count": 2,
        "paths": 2,
        "relevance": 40
      },
      {
        "title": "Russia",
        "count": 2,
        "paths": 2,
        "relevance": 40
      },
      {
        "title": "South America",
        "count": 2,
        "paths": 2,
        "relevance": 40
      },
      {
        "title": "Spain",
        "count": 2,
        "paths": 2,
        "relevance": 40
      },
      {
        "title": "Sweden",
        "count": 2,
        "paths": 2,
        "relevance": 40
      },
      {
        "title": "Switzerland",
        "count": 2,
        "paths": 2,
        "relevance": 40
      },
      {
        "title": "Syria",
        "count": 2,
        "paths": 2,
        "relevance": 40
      },
      {
        "title": "Transcaucasia",
        "count": 2,
        "paths": 2,
        "relevance": 40
      },
      {
        "title": "Turkey and Ancient Anatolia",
        "count": 2,
        "paths": 2,
        "relevance": 40
      },
      {
        "title": "Ukraine",
        "count": 2,
        "paths": 2,
        "relevance": 40
      },
      {
        "title": "United Kingdom",
        "count": 2,
        "paths": 2,
        "relevance": 40
      },
      {
        "title": "United States of America",
        "count": 2,
        "paths": 2,
        "relevance": 40
      },
      {
        "title": "Venice",
        "count": 2,
        "paths": 2,
        "relevance": 40
      },
      {
        "title": "Vienna",
        "count": 2,
        "paths": 2,
        "relevance": 40
      },
      {
        "title": "Warsaw",
        "count": 2,
        "paths": 2,
        "relevance": 40
      }
    ]
  }
}
