{
  "sectionCode": "823",
  "sectionCodeDisplay": "823",
  "title": "Hinduism and Other Religions of India",
  "outline": [
    {
      "level": "A",
      "levelType": "major",
      "text": "History of Hinduism",
      "children": [
        {
          "level": "1",
          "levelType": "numeric",
          "text": "The origins of Hinduism: Indo-European roots and other influences",
          "children": []
        },
        {
          "level": "2",
          "levelType": "numeric",
          "text": "The prehistoric and protohistoric periods, through the 2nd millennium bc: the religions of the indigenous prehistoric peoples and of the Indus Valley civilization",
          "children": []
        },
        {
          "level": "3",
          "levelType": "numeric",
          "text": "The Vedic period (2nd millennium-7th century bc) , a. The religion of the Rgveda",
          "children": [
            {
              "level": "b",
              "levelType": "lowercase",
              "text": "The religion of the later Vedas and Brahmanas",
              "children": []
            },
            {
              "level": "c",
              "levelType": "lowercase",
              "text": "The religion of the Upanisads",
              "children": []
            }
          ]
        },
        {
          "level": "4",
          "levelType": "numeric",
          "text": "The heterodox period (7th-2nd century bc): challenges to Brahmanism by reformers and ascetic groups [see also D.I., below, and 824]",
          "children": []
        },
        {
          "level": "5",
          "levelType": "numeric",
          "text": "The early Hindu period (2nd century BC-4th century ad): the rise of the major sects and other developments",
          "children": []
        },
        {
          "level": "6",
          "levelType": "numeric",
          "text": "The Puranic period (4th-8th century)",
          "children": []
        },
        {
          "level": "7",
          "levelType": "numeric",
          "text": "The rise of devotional Hinduism (8th- 11th century): the Tamil hymnists, the Bhagavata-Purana after Hinduism",
          "children": []
        },
        {
          "level": "8",
          "levelType": "numeric",
          "text": "The age of bhakti (1 1th- 19th century)",
          "children": []
        },
        {
          "level": "9",
          "levelType": "numeric",
          "text": "The modem period (19th-20th century)",
          "children": []
        },
        {
          "level": "10",
          "levelType": "numeric",
          "text": "Hinduism today",
          "children": []
        }
      ]
    },
    {
      "level": "B",
      "levelType": "major",
      "text": "Intellectual, spiritual, and imaginative expressions of Hinduism [see also C.4., below]",
      "children": [
        {
          "level": "1",
          "levelType": "numeric",
          "text": "Hindu sacred literature",
          "children": [
            {
              "level": "a",
              "levelType": "lowercase",
              "text": "Primary scriptures regarded as eternal revelations: the Veda",
              "children": []
            },
            {
              "level": "b",
              "levelType": "lowercase",
              "text": "Post-Vedic Sanskrit literature; e.g., epics, Puranas, Tantras",
              "children": []
            },
            {
              "level": "c",
              "levelType": "lowercase",
              "text": "Sacred literature in Indian regional languages",
              "children": []
            }
          ]
        },
        {
          "level": "2",
          "levelType": "numeric",
          "text": "Hindu mythology: varieties of myths, modes of representation and themes",
          "children": []
        },
        {
          "level": "3",
          "levelType": "numeric",
          "text": "Hindu philosophy: the integral relation of philosophy and religion in Hinduism",
          "children": []
        },
        {
          "level": "4",
          "levelType": "numeric",
          "text": "Hindu mysticism: its general characteristics, varieties, goals, and methods",
          "children": []
        }
      ]
    },
    {
      "level": "C",
      "levelType": "major",
      "text": "Beliefs, practices, and institutions of Hinduism",
      "children": [
        {
          "level": "1",
          "levelType": "numeric",
          "text": "Common characteristics of Hindu belief",
          "children": [
            {
              "level": "a",
              "levelType": "lowercase",
              "text": "Views about God or the sacred",
              "children": []
            },
            {
              "level": "b",
              "levelType": "lowercase",
              "text": "Views about the universe",
              "children": []
            },
            {
              "level": "c",
              "levelType": "lowercase",
              "text": "Views about mankind",
              "children": [
                {
                  "level": "i",
                  "levelType": "lowercase",
                  "text": "Ahimsa, the obligation to respect all living beings",
                  "children": []
                },
                {
                  "level": "ii",
                  "levelType": "roman",
                  "text": "The doctrines of karman, samsara, and transmigration",
                  "children": []
                },
                {
                  "level": "iii",
                  "levelType": "roman",
                  "text": "The three margas : the paths of duties, of knowledge, and of devotion",
                  "children": []
                }
              ]
            }
          ]
        },
        {
          "level": "2",
          "levelType": "numeric",
          "text": "The forms of Hinduism",
          "children": [
            {
              "level": "a",
              "levelType": "lowercase",
              "text": "Vedism and Brahmanism",
              "children": []
            },
            {
              "level": "b",
              "levelType": "lowercase",
              "text": "Vaisnavism",
              "children": []
            },
            {
              "level": "c",
              "levelType": "lowercase",
              "text": "Saivism",
              "children": []
            },
            {
              "level": "d",
              "levelType": "lowercase",
              "text": "Tantrism and Shaktism",
              "children": []
            },
            {
              "level": "e",
              "levelType": "lowercase",
              "text": "Folk Hinduism",
              "children": []
            },
            {
              "level": "f",
              "levelType": "lowercase",
              "text": "Ethical, social, and nationalist movements in modem Hinduism",
              "children": []
            }
          ]
        },
        {
          "level": "3",
          "levelType": "numeric",
          "text": "Rituals, social practices, and institutions",
          "children": [
            {
              "level": "a",
              "levelType": "lowercase",
              "text": "Sacrifice and worship",
              "children": []
            },
            {
              "level": "b",
              "levelType": "lowercase",
              "text": "Sacred times and places",
              "children": []
            },
            {
              "level": "c",
              "levelType": "lowercase",
              "text": "The class hierarchy: the caste system",
              "children": []
            },
            {
              "level": "d",
              "levelType": "lowercase",
              "text": "Religious orders, holy men, the four stages of life",
              "children": []
            }
          ]
        },
        {
          "level": "4",
          "levelType": "numeric",
          "text": "Cultural expressions of Hindu values and ideas",
          "children": [
            {
              "level": "a",
              "levelType": "lowercase",
              "text": "The traditional religious functions of Indian art: symbols and images",
              "children": [
                {
                  "level": "i",
                  "levelType": "lowercase",
                  "text": "Types of symbols: yantras, mandalas, lingas, yonis",
                  "children": []
                },
                {
                  "level": "ii",
                  "levelType": "roman",
                  "text": "Icons: their role in expressing theological elements of Hinduism",
                  "children": []
                }
              ]
            },
            {
              "level": "b",
              "levelType": "lowercase",
              "text": "The religious expression of particular arts",
              "children": []
            }
          ]
        }
      ]
    },
    {
      "level": "D",
      "levelType": "major",
      "text": "Other religions of India",
      "children": [
        {
          "level": "1",
          "levelType": "numeric",
          "text": "Jainism",
          "children": [
            {
              "level": "a",
              "levelType": "lowercase",
              "text": "History of Jainism",
              "children": [
                {
                  "level": "i",
                  "levelType": "lowercase",
                  "text": "Early background: traditional accounts of Mahavlra's predecessors",
                  "children": []
                },
                {
                  "level": "ii",
                  "levelType": "roman",
                  "text": "The life, work, and teachings of Vardhamana Mahavlra",
                  "children": []
                },
                {
                  "level": "iii",
                  "levelType": "roman",
                  "text": "Later developments (6th century Bc-20th century ad)",
                  "children": []
                }
              ]
            },
            {
              "level": "b",
              "levelType": "lowercase",
              "text": "Myths about Jaina \"great souls\": Tirthankaras, ascetic and monastic figures, and lesser deities",
              "children": []
            },
            {
              "level": "c",
              "levelType": "lowercase",
              "text": "Beliefs, practices, and institutions of Jainism",
              "children": []
            }
          ]
        },
        {
          "level": "2",
          "levelType": "numeric",
          "text": "Sikhism",
          "children": [
            {
              "level": "a",
              "levelType": "lowercase",
              "text": "History of Sikhism",
              "children": [
                {
                  "level": "i",
                  "levelType": "lowercase",
                  "text": "Islamic and Hindu background (1 1th- 15th century) [see also A., above, and 828.A.]",
                  "children": []
                },
                {
                  "level": "ii",
                  "levelType": "roman",
                  "text": "The origin of Sikhism in the life and work of Nanak, first of the ten Gurus (15th- 16th century)",
                  "children": []
                },
                {
                  "level": "iii",
                  "levelType": "roman",
                  "text": "The establishment and growth of Sikhism under the nine succeeding Gurus, the establishment of Sikh militarism (16th- 18th century)",
                  "children": []
                },
                {
                  "level": "iv",
                  "levelType": "roman",
                  "text": "The condition of Sikhism during the Sikh empire (18th- 19th century)",
                  "children": []
                }
              ]
            },
            {
              "level": "v",
              "levelType": "lowercase",
              "text": "The condition of Sikhism under British rule (19th-20th century)",
              "children": [
                {
                  "level": "vi",
                  "levelType": "roman",
                  "text": "Sikhism in independent India and Pakistan",
                  "children": []
                }
              ]
            },
            {
              "level": "b",
              "levelType": "lowercase",
              "text": "Sikh religious literature",
              "children": []
            },
            {
              "level": "c",
              "levelType": "lowercase",
              "text": "Beliefs, practices, and institutions of Sikhism",
              "children": []
            }
          ]
        },
        {
          "level": "3",
          "levelType": "numeric",
          "text": "Parsiism: Zoroastrianism in India [see 822.B.4.]",
          "children": [
            {
              "level": "a",
              "levelType": "lowercase",
              "text": "History of Parsiism",
              "children": []
            },
            {
              "level": "b",
              "levelType": "lowercase",
              "text": "Sources of beliefs and doctrines in Zoroastrian literature",
              "children": []
            }
          ]
        }
      ]
    }
  ],
  "crossReferences": [
    {
      "fromPath": "D.3",
      "targetSection": "822",
      "targetPath": "B.4"
    }
  ],
  "macropaediaReferences": [
    "Hinduism",
    "Indian Philosophy",
    "Jainism",
    "Sikhism"
  ],
  "partNumber": 8,
  "divisionId": "8-02"
}
